invokeftp/__init__.py
invokeftp/invokeftp.py
invokeftp-0.0.1.dist-info/METADATA
invokeftp-0.0.1.dist-info/WHEEL
invokeftp-0.0.1.dist-info/top_level.txt
invokeftp-0.0.1.dist-info/RECORD
